pytoniq/__init__.py
pytoniq/adnl/__init__.py
pytoniq/adnl/adnl.py
pytoniq/adnl/dht.py
pytoniq/adnl/overlay.py
pytoniq/contract/__init__.py
pytoniq/contract/contract.py
pytoniq/contract/utils.py
pytoniq/contract/nft/__init__.py
pytoniq/contract/nft/nft.py
pytoniq/contract/nft/nft_sale.py
pytoniq/contract/wallets/__init__.py
pytoniq/contract/wallets/highload.py
pytoniq/contract/wallets/highload_v3.py
pytoniq/contract/wallets/wallet.py
pytoniq/liteclient/__init__.py
pytoniq/liteclient/_balancer_codegen.py
pytoniq/liteclient/balancer.py
pytoniq/liteclient/client.py
pytoniq/liteclient/sync.py
pytoniq/liteclient/utils.py
pytoniq-0.1.41.dist-info/METADATA
pytoniq-0.1.41.dist-info/WHEEL
pytoniq-0.1.41.dist-info/top_level.txt
pytoniq-0.1.41.dist-info/RECORD
