Metadata-Version: 2.4
Name: pytoniq
Version: 0.1.41
Summary: TON Blockchain SDK
Home-page: https://github.com/yungwine/pytoniq
Author: Maksim Kurbatov
Author-email: cyrbatoff@gmail.com
Classifier: Programming Language :: Python :: 3.9
Classifier: Programming Language :: Python :: 3.10
Classifier: Programming Language :: Python :: 3.11
Classifier: Topic :: Software Development :: Libraries
Requires-Python: >=3.9
Requires-Dist: pytoniq-core>=0.1.42
Requires-Dist: requests>=2.31.0
Requires-Dist: setuptools>=65.5.1
Provides-Extra: tvm
Requires-Dist: pytvm>=0.0.11; extra == "tvm"
Dynamic: author
Dynamic: author-email
Dynamic: classifier
Dynamic: description
Dynamic: description-content-type
Dynamic: home-page
Dynamic: provides-extra
Dynamic: requires-dist
Dynamic: requires-python
Dynamic: summary
